README.md
setup.py
ai_code_sandbox/__init__.py
ai_code_sandbox/sandbox.py
ai_code_sandbox.egg-info/PKG-INFO
ai_code_sandbox.egg-info/SOURCES.txt
ai_code_sandbox.egg-info/dependency_links.txt
ai_code_sandbox.egg-info/requires.txt
ai_code_sandbox.egg-info/top_level.txt
tests/test_sandbox.py