Metadata-Version: 2.1
Name: ai-code-sandbox
Version: 0.1.0
Summary: Secure Python sandbox for AI/ML code execution using Docker. Run LLM outputs safely.
Home-page: https://github.com/typper-io/ai-code-sandbox
Author: Typper, Corp.
Author-email: contact@typper.io
Classifier: Development Status :: 3 - Alpha
Classifier: Intended Audience :: Developers
Classifier: License :: OSI Approved :: MIT License
Classifier: Operating System :: OS Independent
Classifier: Programming Language :: Python :: 3
Classifier: Programming Language :: Python :: 3.7
Classifier: Programming Language :: Python :: 3.8
Classifier: Programming Language :: Python :: 3.9
Classifier: Programming Language :: Python :: 3.10
Requires-Python: >=3.7
Requires-Dist: docker
